package_delivery_app/__init__.py
package_delivery_app/__main__.py
package_delivery_app/cli.py
package_delivery_app/load.py
package_delivery_app/classes/__init__.py
package_delivery_app/classes/hash.py
package_delivery_app/classes/package.py
package_delivery_app/classes/route_builder.py
package_delivery_app/classes/route_helpers.py
package_delivery_app/classes/time_custom.py
package_delivery_app/classes/truck.py
package_delivery_app/tests/__init__.py
package_delivery_app/tests/general.py
package_delivery_app/tests/specific_tests/__init__.py
package_delivery_app/tests/specific_tests/algorithms_tests.py
package_delivery_app/tests/specific_tests/hash_tests.py
package_delivery_app/tests/specific_tests/regex_tests.py
package_delivery_app-0.9.3.dist-info/LICENSE.txt
package_delivery_app-0.9.3.dist-info/METADATA
package_delivery_app-0.9.3.dist-info/WHEEL
package_delivery_app-0.9.3.dist-info/top_level.txt
package_delivery_app-0.9.3.dist-info/RECORD
