Metadata-Version: 2.1
Name: package-delivery-app
Version: 0.9.3
Summary: A simulation of package delivery with constraints
Home-page: https://github.com/adamisom/package-delivery-app
Author: Adam Isom
Author-email: adam.r.isom@gmail.com
License: UNKNOWN
Platform: UNKNOWN
Classifier: Programming Language :: Python :: 3
Classifier: License :: OSI Approved :: MIT License
Classifier: Operating System :: OS Independent
Requires-Python: >=3.6
